AUTHORS
CHANGELOG.txt
DESCRIPTION
LICENSE
MANIFEST.in
README.rst
setup.py
django_payslip.egg-info/PKG-INFO
django_payslip.egg-info/SOURCES.txt
django_payslip.egg-info/dependency_links.txt
django_payslip.egg-info/requires.txt
django_payslip.egg-info/top_level.txt
payslip/__init__.py
payslip/admin.py
payslip/app_settings.py
payslip/forms.py
payslip/models.py
payslip/urls.py
payslip/views.py
payslip/fixtures/bootstrap_auth.json
payslip/migrations/0001_initial.py
payslip/migrations/__init__.py
payslip/south_migrations/0001_initial.py
payslip/south_migrations/0002_auto__add_field_employee_is_manager.py
payslip/south_migrations/0003_auto__add_field_extrafieldtype_model__add_field_extrafieldtype_fixed_v.py
payslip/south_migrations/0004_auto__add_field_paymenttype_rrule__chg_field_extrafieldtype_model.py
payslip/south_migrations/0005_auto__add_field_payment_end_date.py
payslip/south_migrations/__init__.py
payslip/static/payslip/css/base.css
payslip/static/payslip/css/payslip.css
payslip/static/payslip/js/payslip.js
payslip/templates/payslip/company_confirm_delete.html
payslip/templates/payslip/company_form.html
payslip/templates/payslip/dashboard.html
payslip/templates/payslip/delete_base.html
payslip/templates/payslip/employee_confirm_delete.html
payslip/templates/payslip/employee_form.html
payslip/templates/payslip/extrafield_confirm_delete.html
payslip/templates/payslip/extrafield_form.html
payslip/templates/payslip/extrafieldtype_confirm_delete.html
payslip/templates/payslip/extrafieldtype_form.html
payslip/templates/payslip/payment_confirm_delete.html
payslip/templates/payslip/payment_form.html
payslip/templates/payslip/paymenttype_confirm_delete.html
payslip/templates/payslip/paymenttype_form.html
payslip/templates/payslip/payslip.html
payslip/templates/payslip/payslip_base.html
payslip/templates/payslip/payslip_form.html
payslip/templatetags/__init__.py
payslip/templatetags/payslip_tags.py
payslip/tests/__init__.py
payslip/tests/forms_tests.py
payslip/tests/models_tests.py
payslip/tests/settings.py
payslip/tests/tag_tests.py
payslip/tests/test_settings.py
payslip/tests/urls.py
payslip/tests/views_tests.py
payslip/tests/test_app/__init__.py
