Metadata-Version: 1.0
Name: django-payslip
Version: 0.3.2
Summary: A reusable Django app that allows you to enter salary data of your employees
